{
  "version": "7",
  "dialect": "sqlite",
  "entries": [
    {
      "idx": 0,
      "version": "6",
      "when": 1771850493381,
      "tag": "0000_clear_dazzler",
      "breakpoints": true
    },
    {
      "idx": 1,
      "version": "6",
      "when": 1771856158785,
      "tag": "0001_wild_red_hulk",
      "breakpoints": true
    },
    {
      "idx": 2,
      "version": "6",
      "when": 1771857228385,
      "tag": "0002_small_killraven",
      "breakpoints": true
    },
    {
      "idx": 3,
      "version": "6",
      "when": 1771858188864,
      "tag": "0003_aspiring_outlaw_kid",
      "breakpoints": true
    },
    {
      "idx": 4,
      "version": "6",
      "when": 1771872398312,
      "tag": "0004_magical_ozymandias",
      "breakpoints": true
    },
    {
      "idx": 5,
      "version": "6",
      "when": 1771996728251,
      "tag": "0005_common_hex",
      "breakpoints": true
    }
  ]
}
